algo_scope/__init__.py
algo_scope/viewer.py
algo_scope/assets/index.html
algo_scope/assets/script.js
algo_scope/assets/style.css
algo_scope-1.0.3.dist-info/METADATA
algo_scope-1.0.3.dist-info/WHEEL
algo_scope-1.0.3.dist-info/top_level.txt
algo_scope-1.0.3.dist-info/RECORD
