Metadata-Version: 2.4
Name: algo-scope
Version: 1.0.3
Summary: Algorithm Explorer – Algo Scope
Home-page: https://github.com/shivendrasingh11249
Author: Shivendra
Author-email: Shivendra <2k22.csai2211760@gmail.com>
License: MIT
Keywords: algorithms,data-structures,python,explorer
Requires-Python: >=3.8
Dynamic: author
Dynamic: home-page
Dynamic: requires-python
